django_progressiveimagefield-0.1.5.dist-info/DESCRIPTION.rst
django_progressiveimagefield-0.1.5.dist-info/METADATA
django_progressiveimagefield-0.1.5.dist-info/RECORD
django_progressiveimagefield-0.1.5.dist-info/WHEEL
django_progressiveimagefield-0.1.5.dist-info/metadata.json
django_progressiveimagefield-0.1.5.dist-info/top_level.txt
progressiveimagefield/__init__.py
progressiveimagefield/apps.py
progressiveimagefield/fields.py
progressiveimagefield/jinja/__init__.py
progressiveimagefield/jinja/filters.py
progressiveimagefield/static/progressiveimagefield/css/pif.css
progressiveimagefield/static/progressiveimagefield/js/pif.js
progressiveimagefield/templates/progressiveimagefield/render_field.html
progressiveimagefield/templatetags/__init__.py
progressiveimagefield/templatetags/progressive_tags.py
