Metadata-Version: 2.0
Name: django-progressiveimagefield
Version: 0.1.5
Summary: A Django ImageField that offers progressive                 image loading during HTML rendering.
Home-page: https://github.com/manikos/django-progressiveimagefield
Author: Nick Mavrakis
Author-email: mavrakis.n@gmail.com
License: UNKNOWN
Keywords: django progressive image field
Platform: UNKNOWN
Classifier: Development Status :: 5 - Production/Stable
Classifier: Environment :: Web Environment
Classifier: Framework :: Django
Classifier: Framework :: Django :: 2.0
Classifier: Framework :: Django :: 2.1
Classifier: Intended Audience :: Developers
Classifier: License :: OSI Approved :: MIT License
Classifier: Natural Language :: English
Classifier: Operating System :: OS Independent
Classifier: Programming Language :: Python
Classifier: Programming Language :: Python :: 3.6
Requires-Python: >=3.6
Requires-Dist: Django (>=2.0.11)
Requires-Dist: Pillow (>=4.0.0)
